Workbook

Sheet Historical Analysis
A1: COSTCO WHOLESALE CORPORATION (COST)
A2: Historical Analysis — FY2023A to FY2025A
A3: All figures in $mm unless noted | CAGR = 2-year (FY2023→FY2025)
B4: FY2023A | C4: FY2024A | D4: FY2025A | E4: 2-Yr CAGR
A5: INCOME STATEMENT
A6: Net Sales | B6: 237710 | C6: 249625 | D6: 269912 | E6: =(D6/B6)^(1/2)-1 -> 0.065583214
A7: Membership Fees | B7: 4580 | C7: 4828 | D7: 5323 | E7: =(D7/B7)^(1/2)-1 -> 0.078066359
A8: Total Revenue | B8: 242290 | C8: 254453 | D8: 275235 | E8: =(D8/B8)^(1/2)-1 -> 0.065820538
A9: Merchandise Costs | B9: 212586 | C9: 222358 | D9: 239886 | E9: =(D9/B9)^(1/2)-1 -> 0.062270501
A10: Gross Profit | B10: 29704 | C10: 32095 | D10: 35349 | E10: =(D10/B10)^(1/2)-1 -> 0.090890345
A11: SG&A Expenses | B11: 21590 | C11: 22810 | D11: 24966 | E11: =(D11/B11)^(1/2)-1 -> 0.075345846
A12: Operating Income | B12: 8114 | C12: 9285 | D12: 10383 | E12: =(D12/B12)^(1/2)-1 -> 0.1312118
A13: Net Income | B13: 6292 | C13: 7367 | D13: 8099 | E13: =(D13/B13)^(1/2)-1 -> 0.134544
A14: Diluted EPS ($) | B14: 14.16 | C14: 16.56 | D14: 18.21 | E14: =(D14/B14)^(1/2)-1 -> 0.13402687
A16: KEY MARGINS
A17: Merchandise Margin % | B17: 0.1057 | C17: 0.1092 | D17: 0.1112
A18: Gross Margin % (Total Rev) | B18: 0.1226 | C18: 0.1261 | D18: 0.1285
A19: SG&A % of Net Sales | B19: 0.0908 | C19: 0.0914 | D19: 0.0925
A20: Operating Margin % | B20: 0.0335 | C20: 0.0365 | D20: 0.0377
A21: Net Margin % | B21: 0.026 | C21: 0.029 | D21: 0.0294
A22: Effective Tax Rate | B22: 0.259 | C22: 0.244 | D22: 0.251
A24: CASH FLOW
A25: Operating Cash Flow | B25: 11068 | C25: 11339 | D25: 13335 | E25: =(D25/B25)^(1/2)-1 -> 0.097645079
A26: Capital Expenditures | B26: 4323 | C26: 4710 | D26: 5498 | E26: =(D26/B26)^(1/2)-1 -> 0.12774199
A27: Free Cash Flow | B27: 6745 | C27: 6629 | D27: 7837 | E27: =(D27/B27)^(1/2)-1 -> 0.077913587
A28: D&A | B28: 2489 | C28: 2237 | D28: 2426 | E28: =(D28/B28)^(1/2)-1 -> -0.012736798
A29: EBITDA | B29: 10603 | C29: 11522 | D29: 12809 | E29: =(D29/B29)^(1/2)-1 -> 0.099115246
A31: OPERATIONAL KPIs
A32: Total Warehouses | B32: 861 | C32: 890 | D32: 914 | E32: =(D32/B32)^(1/2)-1 -> 0.030318557
A33: Net New Warehouses | B33: 23 | C33: 29 | D33: 24 | E33: =(D33/B33)^(1/2)-1 -> 0.021507837
A34: Total Paid Members (mm) | B34: 71 | C34: 76.2 | D34: 81 | E34: =(D34/B34)^(1/2)-1 -> 0.068103492
A35: Executive Members (mm) | B35: 32.3 | C35: 35.4 | D35: 38.7 | E35: =(D35/B35)^(1/2)-1 -> 0.094596919
A36: Total Cardholders (mm) | B36: 127.9 | C36: 136.8 | D36: 145.2 | E36: =(D36/B36)^(1/2)-1 -> 0.065486707
A37: Worldwide Renewal Rate | B37: 0.904 | C37: 0.905 | D37: 0.898
A38: Exec Sales Penetration | B38: 0.718 | C38: 0.731 | D38: 0.736
A39: Rev per Warehouse ($mm, Avg) | B39: 279.8 | C39: 285.1 | D39: 299.2 | E39: =(D39/B39)^(1/2)-1 -> 0.034086669

Sheet Revenue Drivers
A1: COSTCO WHOLESALE CORPORATION (COST)
A2: Revenue Driver Decomposition
A3: All figures in $mm unless noted
B4: FY2023A | C4: FY2024A | D4: FY2025A | E4: FY2026E | F4: FY2027E | G4: Notes
A5: DRIVER 1: WAREHOUSE COUNT × REVENUE PER WAREHOUSE
A6: Beginning Warehouses | B6: 838 | C6: 861 | D6: 890 | E6: =Assumptions!D6 -> 914 | F6: =Assumptions!E6 -> 944 | G6: FactSet / 10-K
A7: Gross New Openings | B7: 26 | C7: 30 | D7: 27
A8: Net New Warehouses | B8: 23 | C8: 29 | D8: 24 | E8: =Assumptions!E7 -> 30 | F8: =Assumptions!F7 -> 28 | G8: 10-K: up to 35 incl 5 relocs for FY26
A9: Ending Warehouses | B9: 861 | C9: 890 | D9: 914 | E9: =Assumptions!E6 -> 944 | F9: =Assumptions!F6 -> 972
A10: Average Warehouses | B10: 849.5 | C10: 875.5 | D10: 902 | E10: =(D9+E9)/2 -> 929 | F10: =(E9+F9)/2 -> 958
A11: Net Sales ($mm) | B11: 237710 | C11: 249625 | D11: 269912 | E11: ='Income Statement'!E6 -> 291504.96 | F11: ='Income Statement'!F6 -> 311910.31
A12: Rev per Warehouse ($mm, Avg basis) | B12: =B11/B10 -> 279.82343 | C12: =C11/C10 -> 285.12279 | D12: =D11/D10 -> 299.23725 | E12: =E11/E10 -> 313.7836 | F12: =F11/F10 -> 325.58487 | G12: Net Sales / Avg Warehouses
A13: Rev per Warehouse Growth | C13: =(C12-B12)/B12 -> 0.018938234 | D13: =(D12-C12)/C12 -> 0.049503106 | E13: =(E12-D12)/D12 -> 0.04861141 | F13: =(F12-E12)/E12 -> 0.037609603
A15: DRIVER 2: MEMBERSHIP ENGINE
A16: Gold Star Members (mm) | B16: 58.8 | C16: 63.7 | D16: 68.3 | E16: =Assumptions!E15 -> 72.8 | F16: =Assumptions!F15 -> 77 | G16: 10-K FY2025 p.5
A17: Business incl. Affiliates (mm) | B17: 12.2 | C17: 12.5 | D17: 12.7 | E17: =Assumptions!E16 -> 13.1 | F17: =Assumptions!F16 -> 13.4
A18: Total Paid Members (mm) | B18: 71 | C18: 76.2 | D18: 81 | E18: =Assumptions!E13 -> 85.86 | F18: =Assumptions!F13 -> 90.5823
A19: Executive Members (mm) | B19: 32.3 | C19: 35.4 | D19: 38.7 | E19: =Assumptions!E17 -> 41.8 | F19: =Assumptions!F17 -> 44.5
A20: Total Cardholders (mm) | B20: 127.9 | C20: 136.8 | D20: 145.2 | E20: =Assumptions!E18 -> 153.5 | F20: =Assumptions!F18 -> 161
A21: Worldwide Renewal Rate (%) | B21: 0.904 | C21: 0.905 | D21: 0.898 | E21: =Assumptions!E20 -> 0.899 | F21: =Assumptions!F20 -> 0.9
A22: Annual Fee ($) | B22: =Assumptions!B19 -> 60 | C22: =Assumptions!C19 -> 60 | D22: =Assumptions!D19 -> 65 | E22: =Assumptions!E19 -> 65 | F22: =Assumptions!F19 -> 65 | G22: Increased to $65 eff. Sep 1, 2024
A23: Membership Fee Revenue ($mm) | B23: 4580 | C23: 4828 | D23: 5323 | E23: ='Income Statement'!E7 -> 5695.61 | F23: ='Income Statement'!F7 -> 6037.3466
A24: Implied Fee per Paid Member ($) | B24: =B23/B18 -> 64.507042 | C24: =C23/C18 -> 63.35958 | D24: =D23/D18 -> 65.716049 | E24: =E23/E18 -> 66.336012 | F24: =F23/F18 -> 66.650401 | G24: Implied = Fees / Total Paid Members
A25: Executive Penetration (% of Paid) | B25: =B19/B18 -> 0.45492958 | C25: =C19/C18 -> 0.46456693 | D25: =D19/D18 -> 0.47777778 | E25: =E19/E18 -> 0.48683904 | F25: =F19/F18 -> 0.49126595
A27: DRIVER 3: MARGIN STRUCTURE
A28: Merchandise Margin % | B28: =Assumptions!B26 -> 0.1057 | C28: =Assumptions!C26 -> 0.1092 | D28: =Assumptions!D26 -> 0.1112 | E28: =Assumptions!E26 -> 0.112 | F28: =Assumptions!F26 -> 0.1125 | G28: (Net Sales - COGS) / Net Sales
A29: SG&A % of Net Sales | B29: =Assumptions!B27 -> 0.0908 | C29: =Assumptions!C27 -> 0.0914 | D29: =Assumptions!D27 -> 0.0925 | E29: =Assumptions!E27 -> 0.0928 | F29: =Assumptions!F27 -> 0.093
A30: Operating Margin % | B30: ='Income Statement'!B29 -> 0.033488794 | C30: ='Income Statement'!C29 -> 0.036490039 | D30: ='Income Statement'!D29 -> 0.037724127 | E30: ='Income Statement'!E29 -> 0.037996244 | F30: ='Income Statement'!F29 -> 0.038118217 | G30: Operating Income / Total Revenue
A32: 10-K REFERENCE: AVG SALES PER WAREHOUSE (p.22)
A33: 10-K Avg Sales/Warehouse (Total) | B33: 252 | C33: 260 | D33: 272 | G33: Source: 10-K FY2025, p.22
A34: Mature Stores (2016 & Before, 715 whses) | B34: 263 | C34: 274 | D34: 287 | G34: 10-yr CAGR ~6.8% ($159 to $287mm)
A35: New Stores (FY2023 cohort, 23 whses) | B35: 151 | C35: 166 | D35: 186 | G35: Ramp to ~65% mature level by Yr 3
A36: New Store Ramp (% of Mature) | B36: =B35/B34 -> 0.57414449 | C36: =C35/C34 -> 0.60583942 | D36: =D35/D34 -> 0.64808362 | G36: FY2023 cohort vs mature stores

Sheet Assumptions
A1: COSTCO WHOLESALE CORPORATION (COST)
A2: Driver-Based Forecast — Assumption Inputs
A3: All monetary figures in $mm unless noted
B4: FY2023A | C4: FY2024A | D4: FY2025A | E4: FY2026E | F4: FY2027E | G4: Source / Notes
A5: REVENUE DRIVERS
A6: Total Warehouses (EOY) | B6: 861 | C6: 890 | D6: 914 | E6: =D6+E7 -> 944 | F6: =E6+F7 -> 972 | G6: Source: 10-K FY2025, p.4
A7: Net New Warehouses | B7: 23 | C7: 29 | D7: 24 | E7: 30 | F7: 28 | G7: 10-K: up to 35 incl. 5 relocs for FY2026
A8: Net Sales Growth (%) | B8: 0.07 | C8: 0.05 | D8: 0.08 | E8: 0.08 | F8: 0.07 | G8: FY25 was 8%; modeled 8%/7% on comp + new stores
A9: Comparable Sales Growth (%) | B9: 0.03 | C9: 0.05 | D9: 0.06 | E9: 0.07 | F9: 0.06 | G9: 10-K: FY25 6% reported, 8% ex-FX/gas
A10: Net Sales per Warehouse ($mm, Avg) | B10: 279.8 | C10: 285.1 | D10: 299.2 | E10: ='Revenue Drivers'!E12 -> 313.7836 | F10: ='Revenue Drivers'!F12 -> 325.58487 | G10: Net Sales / Avg Warehouses (Beg+End)/2
A12: MEMBERSHIP DRIVERS
A13: Total Paid Members (mm) | B13: 71 | C13: 76.2 | D13: 81 | E13: =D13*(1+E14) -> 85.86 | F13: =E13*(1+F14) -> 90.5823 | G13: 10-K FY2025 p.5: 81,000K paid members
A14: Paid Member Growth (%) | C14: =(C13-B13)/B13 -> 0.073239437 | D14: =(D13-C13)/C13 -> 0.062992126 | E14: 0.06 | F14: 0.055
A15: Gold Star Members (mm) | B15: 58.8 | C15: 63.7 | D15: 68.3 | E15: 72.8 | F15: 77 | G15: 10-K FY2025 p.5
A16: Business incl. Affiliates (mm) | B16: 12.2 | C16: 12.5 | D16: 12.7 | E16: 13.1 | F16: 13.4
A17: Executive Members (mm) | B17: 32.3 | C17: 35.4 | D17: 38.7 | E17: 41.8 | F17: 44.5 | G17: Exec penetration: ~48% of paid (rising)
A18: Total Cardholders (mm) | B18: 127.9 | C18: 136.8 | D18: 145.2 | E18: 153.5 | F18: 161
A19: Annual Membership Fee ($) | B19: 60 | C19: 60 | D19: 65 | E19: 65 | F19: 65 | G19: Increased to $65 eff. Sep 1, 2024 (FY2025)
A20: Worldwide Renewal Rate (%) | B20: 0.904 | C20: 0.905 | D20: 0.898 | E20: 0.899 | F20: 0.9 | G20: 10-K: 89.8% worldwide FY2025
A21: Implied Fee per Paid Member ($) | B21: 64.51 | C21: 63.36 | D21: 65.72 | E21: ='Income Statement'!E7/E13 -> 66.336012 | F21: ='Income Statement'!F7/F13 -> 66.650401
A22: Membership Fee Growth (%) | C22: 0.054 | D22: 0.102 | E22: 0.07 | F22: 0.06 | G22: FY25 10% incl fee hike; ~7%/6% normalized
A23: Exec Sales Penetration (%) | B23: 0.718 | C23: 0.731 | D23: 0.736 | E23: 0.742 | F23: 0.748 | G23: 10-K: 73.6% of net sales FY2025
A25: MARGIN STRUCTURE
A26: Merchandise Margin % (Net Sales) | B26: 0.1057 | C26: 0.1092 | D26: 0.1112 | E26: 0.112 | F26: 0.1125 | G26: Trend: +20bps FY25; +8bps / +5bps est.
A27: SG&A % of Net Sales | B27: 0.0908 | C27: 0.0914 | D27: 0.0925 | E27: 0.0928 | F27: 0.093 | G27: Trend: +6bps, +11bps; assume +3bps, +2bps (scale partially offsets wage pressure)
A29: BELOW THE LINE
A30: Interest Expense ($mm) | B30: 160 | C30: 169 | D30: 154 | E30: 150 | F30: 145 | G30: Declining as Senior Notes mature
A31: Interest Income & Other, net ($mm) | B31: 533 | C31: 624 | D31: 589 | E31: 550 | F31: 525 | G31: Lower rates offset by higher cash
A32: Effective Tax Rate (%) | B32: 0.259 | C32: 0.244 | D32: 0.251 | E32: 0.25 | F32: 0.25 | G32: FY24 low due to special div 401k benefit
A34: CASH FLOW & SHARE DATA
A35: D&A incl. Non-Cash Lease Exp ($mm) | B35: 2489 | C35: 2237 | D35: 2426 | E35: 2600 | F35: 2780 | G35: 10-K CF: D&A + non-cash lease exp
A36: Stock-Based Compensation ($mm) | B36: 774 | C36: 818 | D36: 860 | E36: 900 | F36: 940 | G36: 10-K Note 7; ~5% annual growth
A37: Capital Expenditures ($mm) | B37: 4323 | C37: 4710 | D37: 5498 | E37: 6250 | F37: 6500 | G37: 10-K: $6,000-$6,500 guided for FY2026
A38: Working Capital Change ($mm) | B38: 1018 | C38: 611 | D38: 1764 | E38: 800 | F38: 700 | G38: 10-K CF; positive = source of cash
A39: Other Operating CF Items ($mm) | B39: 495 | C39: 306 | D39: 186 | E39: 300 | F39: 300 | G39: Plug: deferred tax, impairments, other
A40: Diluted Shares Outstanding (mm) | B40: 444.452 | C40: 444.759 | D40: 444.803 | E40: 445 | F40: 445.2 | G40: RSU dilution offset by buybacks
A42: COLOR LEGEND:
A43: Blue = Hardcoded actuals (10-K / FactSet verified)
A44: Green = Formula / calculated from other cells
A45: Grey + Yellow highlight = Estimated assumptions (key inputs to change)

Sheet Income Statement
A1: COSTCO WHOLESALE CORPORATION (COST)
A2: Consolidated Income Statement ($mm)
A3: Source: 10-K FY2025 (Actuals) | Driver-Based Model (Estimates)
B4: FY2023A | C4: FY2024A | D4: FY2025A | E4: FY2026E | F4: FY2027E
A5: REVENUE
A6: Net Sales | B6: 237710 | C6: 249625 | D6: 269912 | E6: =D6*(1+Assumptions!E8) -> 291504.96 | F6: =E6*(1+Assumptions!F8) -> 311910.31
A7: Membership Fees | B7: 4580 | C7: 4828 | D7: 5323 | E7: =D7*(1+Assumptions!E22) -> 5695.61 | F7: =E7*(1+Assumptions!F22) -> 6037.3466
A8: Total Revenue | B8: =B6+B7 -> 242290 | C8: =C6+C7 -> 254453 | D8: =D6+D7 -> 275235 | E8: =E6+E7 -> 297200.57 | F8: =F6+F7 -> 317947.65
A9: OPERATING EXPENSES
A10: Merchandise Costs | B10: 212586 | C10: 222358 | D10: 239886 | E10: =E6*(1-Assumptions!E26) -> 258856.4 | F10: =F6*(1-Assumptions!F26) -> 276820.4
A11: Gross Profit | B11: =B8-B10 -> 29704 | C11: =C8-C10 -> 32095 | D11: =D8-D10 -> 35349 | E11: =E8-E10 -> 38344.166 | F11: =F8-F10 -> 41127.256
A12: Selling, General & Administrative | B12: 21590 | C12: 22810 | D12: 24966 | E12: =E6*Assumptions!E27 -> 27051.66 | F12: =F6*Assumptions!F27 -> 29007.659
A13: Operating Income (EBIT) | B13: =B11-B12 -> 8114 | C13: =C11-C12 -> 9285 | D13: =D11-D12 -> 10383 | E13: =E11-E12 -> 11292.505 | F13: =F11-F12 -> 12119.598
A14: OTHER INCOME / (EXPENSE)
A15: Interest Expense | B15: =-Assumptions!B30 -> -160 | C15: =-Assumptions!C30 -> -169 | D15: =-Assumptions!D30 -> -154 | E15: =-Assumptions!E30 -> -150 | F15: =-Assumptions!F30 -> -145
A16: Interest Income & Other, net | B16: =Assumptions!B31 -> 533 | C16: =Assumptions!C31 -> 624 | D16: =Assumptions!D31 -> 589 | E16: =Assumptions!E31 -> 550 | F16: =Assumptions!F31 -> 525
A17: BOTTOM LINE
A18: Income Before Income Taxes | B18: =B13+B15+B16 -> 8487 | C18: =C13+C15+C16 -> 9740 | D18: =D13+D15+D16 -> 10818 | E18: =E13+E15+E16 -> 11692.505 | F18: =F13+F15+F16 -> 12499.598
A19: Provision for Income Taxes | B19: 2195 | C19: 2373 | D19: 2719 | E19: =E18*Assumptions!E32 -> 2923.1263 | F19: =F18*Assumptions!F32 -> 3124.8994
A20: Net Income | B20: =B18-B19 -> 6292 | C20: =C18-C19 -> 7367 | D20: =D18-D19 -> 8099 | E20: =E18-E19 -> 8769.3789 | F20: =F18-F19 -> 9374.6982
A21: PER SHARE DATA
A22: Diluted EPS ($) | B22: =B20/Assumptions!B40 -> 14.156759 | C22: =C20/Assumptions!C40 -> 16.564027 | D22: =D20/Assumptions!D40 -> 18.208061 | E22: =E20/Assumptions!E40 -> 19.706469 | F22: =F20/Assumptions!F40 -> 21.057274
A23: Diluted Shares (mm) | B23: =Assumptions!B40 -> 444.452 | C23: =Assumptions!C40 -> 444.759 | D23: =Assumptions!D40 -> 444.803 | E23: =Assumptions!E40 -> 445 | F23: =Assumptions!F40 -> 445.2
A25: KEY MARGINS & GROWTH
A26: Merchandise Margin % | B26: =(B6-B10)/B6 -> 0.10569181 | C26: =(C6-C10)/C6 -> 0.10923185 | D26: =(D6-D10)/D6 -> 0.11124366 | E26: =(E6-E10)/E6 -> 0.112 | F26: =(F6-F10)/F6 -> 0.1125
A27: Gross Margin % (Total Rev) | B27: =B11/B8 -> 0.12259689 | C27: =C11/C8 -> 0.12613331 | D27: =D11/D8 -> 0.12843207 | E27: =E11/E8 -> 0.12901781 | F27: =F11/F8 -> 0.12935229
A28: SG&A % of Net Sales | B28: =B12/B6 -> 0.090824955 | C28: =C12/C6 -> 0.091377066 | D28: =D12/D6 -> 0.092496814 | E28: =E12/E6 -> 0.0928 | F28: =F12/F6 -> 0.093
A29: Operating Margin % | B29: =B13/B8 -> 0.033488794 | C29: =C13/C8 -> 0.036490039 | D29: =D13/D8 -> 0.037724127 | E29: =E13/E8 -> 0.037996244 | F29: =F13/F8 -> 0.038118217
A30: Net Margin % | B30: =B20/B8 -> 0.02596888 | C30: =C20/C8 -> 0.028952302 | D30: =D20/D8 -> 0.029425763 | E30: =E20/E8 -> 0.029506602 | F30: =F20/F8 -> 0.029485037
A31: Effective Tax Rate | B31: =B19/B18 -> 0.25863085 | C31: =C19/C18 -> 0.2436345 | D31: =D19/D18 -> 0.25134036 | E31: =E19/E18 -> 0.25 | F31: =F19/F18 -> 0.25
A33: Net Sales Growth | C33: =(C6-B6)/B6 -> 0.050124101 | D33: =(D6-C6)/C6 -> 0.081269905 | E33: =(E6-D6)/D6 -> 0.08 | F33: =(F6-E6)/E6 -> 0.07
A34: Total Revenue Growth | C34: =(C8-B8)/B8 -> 0.050200173 | D34: =(D8-C8)/C8 -> 0.081673236 | E34: =(E8-D8)/D8 -> 0.079806602 | F34: =(F8-E8)/E8 -> 0.069808358
A35: Operating Income Growth | C35: =(C13-B13)/B13 -> 0.14431846 | D35: =(D13-C13)/C13 -> 0.11825525 | E35: =(E13-D13)/D13 -> 0.087595611 | F35: =(F13-E13)/E13 -> 0.073242592
A36: Net Income Growth | C36: =(C20-B20)/B20 -> 0.17085188 | D36: =(D20-C20)/C20 -> 0.09936202 | E36: =(E20-D20)/D20 -> 0.082773049 | F36: =(F20-E20)/E20 -> 0.06902647
A37: EPS Growth | C37: =(C22-B22)/B22 -> 0.17004368 | D37: =(D22-C22)/C22 -> 0.099253271 | E37: =(E22-D22)/D22 -> 0.082293709 | F37: =(F22-E22)/E22 -> 0.068546224
A38: SUPPLEMENTAL
A39: EBITDA | B39: =B13+Assumptions!B35 -> 10603 | C39: =C13+Assumptions!C35 -> 11522 | D39: =D13+Assumptions!D35 -> 12809 | E39: =E13+Assumptions!E35 -> 13892.505 | F39: =F13+Assumptions!F35 -> 14899.598

Sheet Scenario Analysis
A1: COSTCO WHOLESALE CORPORATION (COST)
A2: FY2027E Scenario Analysis
A3: Three scenarios applied to FY2027E using FY2026E Base Case as starting point
B4: Bear Case | C4: Base Case | D4: Bull Case | E4: FY2026E Base
A5: SCENARIO ASSUMPTIONS
A6: Net Sales Growth (%) | B6: 0.05 | C6: 0.07 | D6: 0.1 | E6: =Assumptions!E8 -> 0.08
A7: Membership Fee Growth (%) | B7: 0.05 | C7: 0.06 | D7: 0.08 | E7: =Assumptions!E22 -> 0.07
A8: Merchandise Margin (%) | B8: 0.1105 | C8: 0.1125 | D8: 0.1135 | E8: =Assumptions!E26 -> 0.112
A9: SG&A % of Net Sales | B9: 0.0935 | C9: 0.093 | D9: 0.0922 | E9: =Assumptions!E27 -> 0.0928
A10: Effective Tax Rate (%) | B10: 0.255 | C10: 0.25 | D10: 0.245 | E10: =Assumptions!E32 -> 0.25
A11: Interest Expense ($mm) | B11: 150 | C11: 145 | D11: 140 | E11: =Assumptions!E30 -> 150
A12: Interest Income & Other ($mm) | B12: 500 | C12: 525 | D12: 550 | E12: =Assumptions!E31 -> 550
A14: FY2027E PROJECTED P&L ($mm)
A15: Net Sales | B15: ='Income Statement'!E6*(1+B6) -> 306080.21 | C15: ='Income Statement'!E6*(1+C6) -> 311910.31 | D15: ='Income Statement'!E6*(1+D6) -> 320655.46 | E15: ='Income Statement'!E6 -> 291504.96
A16: Membership Fees | B16: ='Income Statement'!E7*(1+B7) -> 5980.3905 | C16: ='Income Statement'!E7*(1+C7) -> 6037.3466 | D16: ='Income Statement'!E7*(1+D7) -> 6151.2588 | E16: ='Income Statement'!E7 -> 5695.61
A17: Total Revenue | B17: =B15+B16 -> 312060.6 | C17: =C15+C16 -> 317947.65 | D17: =D15+D16 -> 326806.71 | E17: =E15+E16 -> 297200.57
A18: Merchandise Costs | B18: =B15*(1-B8) -> 272258.35 | C18: =C15*(1-C8) -> 276820.4 | D18: =D15*(1-D8) -> 284261.06 | E18: ='Income Statement'!E10 -> 258856.4
A19: Gross Profit | B19: =B17-B18 -> 39802.253 | C19: =C17-C18 -> 41127.256 | D19: =D17-D18 -> 42545.653 | E19: =E17-E18 -> 38344.166
A20: SG&A Expenses | B20: =B15*B9 -> 28618.499 | C20: =C15*C9 -> 29007.659 | D20: =D15*D9 -> 29564.433 | E20: ='Income Statement'!E12 -> 27051.66
A21: Operating Income | B21: =B19-B20 -> 11183.754 | C21: =C19-C20 -> 12119.598 | D21: =D19-D20 -> 12981.22 | E21: =E19-E20 -> 11292.505
A22: Pretax Income | B22: =B21-B11+B12 -> 11533.754 | C22: =C21-C11+C12 -> 12499.598 | D22: =D21-D11+D12 -> 13391.22 | E22: ='Income Statement'!E18 -> 11692.505
A23: Net Income | B23: =B22*(1-B10) -> 8592.6468 | C23: =C22*(1-C10) -> 9374.6982 | D23: =D22*(1-D10) -> 10110.371 | E23: ='Income Statement'!E20 -> 8769.3789
A24: Diluted EPS ($) | B24: =B23/Assumptions!F40 -> 19.300644 | C24: =C23/Assumptions!F40 -> 21.057274 | D24: =D23/Assumptions!F40 -> 22.709728 | E24: ='Income Statement'!E22 -> 19.706469
A26: SCENARIO MARGINS
A27: Operating Margin % | B27: =B21/B17 -> 0.035838405 | C27: =C21/C17 -> 0.038118217 | D27: =D21/D17 -> 0.039721399 | E27: =E21/E17 -> 0.037996244
A28: Net Margin % | B28: =B23/B17 -> 0.027535186 | C28: =C23/C17 -> 0.029485037 | D28: =D23/D17 -> 0.030936852 | E28: =E23/E17 -> 0.029506602
A29: EPS vs Base Case | B29: =(B24-C24)/C24 -> -0.083421505 | C29: 0 | D29: =(D24-C24)/C24 -> 0.078474304

Sheet FCF & Valuation
A1: COSTCO WHOLESALE CORPORATION (COST)
A2: Free Cash Flow Build & Implied Valuation
A3: All figures in $mm unless noted
B4: FY2023A | C4: FY2024A | D4: FY2025A | E4: FY2026E | F4: FY2027E
A5: FREE CASH FLOW BUILD
A6: Net Income | B6: ='Income Statement'!B20 -> 6292 | C6: ='Income Statement'!C20 -> 7367 | D6: ='Income Statement'!D20 -> 8099 | E6: ='Income Statement'!E20 -> 8769.3789 | F6: ='Income Statement'!F20 -> 9374.6982
A7: (+) Depreciation & Amortization | B7: =Assumptions!B35 -> 2489 | C7: =Assumptions!C35 -> 2237 | D7: =Assumptions!D35 -> 2426 | E7: =Assumptions!E35 -> 2600 | F7: =Assumptions!F35 -> 2780
A8: (+) Stock-Based Compensation | B8: =Assumptions!B36 -> 774 | C8: =Assumptions!C36 -> 818 | D8: =Assumptions!D36 -> 860 | E8: =Assumptions!E36 -> 900 | F8: =Assumptions!F36 -> 940
A9: (+/-) Working Capital Changes | B9: =Assumptions!B38 -> 1018 | C9: =Assumptions!C38 -> 611 | D9: =Assumptions!D38 -> 1764 | E9: =Assumptions!E38 -> 800 | F9: =Assumptions!F38 -> 700
A10: (+) Other Operating Items | B10: =Assumptions!B39 -> 495 | C10: =Assumptions!C39 -> 306 | D10: =Assumptions!D39 -> 186 | E10: =Assumptions!E39 -> 300 | F10: =Assumptions!F39 -> 300
A11: Operating Cash Flow | B11: =SUM(B6:B10) -> 11068 | C11: =SUM(C6:C10) -> 11339 | D11: =SUM(D6:D10) -> 13335 | E11: =SUM(E6:E10) -> 13369.379 | F11: =SUM(F6:F10) -> 14094.698
A12: (-) Capital Expenditures | B12: =-Assumptions!B37 -> -4323 | C12: =-Assumptions!C37 -> -4710 | D12: =-Assumptions!D37 -> -5498 | E12: =-Assumptions!E37 -> -6250 | F12: =-Assumptions!F37 -> -6500
A13: Free Cash Flow (Levered) | B13: =B11+B12 -> 6745 | C13: =C11+C12 -> 6629 | D13: =D11+D12 -> 7837 | E13: =E11+E12 -> 7119.3789 | F13: =F11+F12 -> 7594.6982
A14: FCF Margin (% of Total Rev) | B14: =B13/'Income Statement'!B8 -> 0.027838541 | C14: =C13/'Income Statement'!C8 -> 0.026051962 | D14: =D13/'Income Statement'!D8 -> 0.02847385 | E14: =E13/'Income Statement'!E8 -> 0.023954796 | F14: =F13/'Income Statement'!F8 -> 0.023886631
A15: FCF per Share ($) | B15: =B13/Assumptions!B40 -> 15.175992 | C15: =C13/Assumptions!C40 -> 14.904701 | D15: =D13/Assumptions!D40 -> 17.619036 | E15: =E13/Assumptions!E40 -> 15.998604 | F15: =F13/Assumptions!F40 -> 17.059071
A16: EBITDA | B16: ='Income Statement'!B39 -> 10603 | C16: ='Income Statement'!C39 -> 11522 | D16: ='Income Statement'!D39 -> 12809 | E16: ='Income Statement'!E39 -> 13892.505 | F16: ='Income Statement'!F39 -> 14899.598
A18: IMPLIED VALUATION — FY2027E
A19: VALUATION INPUTS
A20: Current Share Price ($ as of Feb 2026) | B20: 1005.3
A21: Diluted Shares (mm) | B21: =Assumptions!F40 -> 445.2
A22: Market Cap ($mm) | B22: =B20*B21 -> 447559.56
A23: Total Debt ($mm) — FY2025 | B23: 9935
A24: Cash & ST Investments ($mm) — FY2025 | B24: 15284
A25: Net Debt ($mm) | B25: =B23-B24 -> -5349
A26: Enterprise Value ($mm) | B26: =B22+B25 -> 442210.56
A28: CURRENT TRAILING MULTIPLES
A29: Trailing P/E (on FY2025 EPS) | B29: =B20/'Income Statement'!D22 -> 55.211811
A30: Trailing EV/EBITDA (on FY2025) | B30: =B26/'Income Statement'!D39 -> 34.523426
A32: FY2027E IMPLIED SHARE PRICE
B33: Bear | C33: Base | D33: Bull
A34: Forward P/E Multiple | B34: 35 | C34: 50 | D34: 58
A35: FY2027E EPS (Base Case) | B35: ='Income Statement'!F22 -> 21.057274 | C35: ='Income Statement'!F22 -> 21.057274 | D35: ='Income Statement'!F22 -> 21.057274
A36: Implied Price (P/E) | B36: =B34*B35 -> 737.00457 | C36: =C34*C35 -> 1052.8637 | D36: =D34*D35 -> 1221.3219
A37: Upside / (Downside) vs Current | B37: =(B36-$B$20)/$B$20 -> -0.26688096 | C37: =(C36-$B$20)/$B$20 -> 0.04731292 | D37: =(D36-$B$20)/$B$20 -> 0.21488299
A39: Forward EV/EBITDA Multiple | B39: 30 | C39: 34 | D39: 38
A40: FY2027E EBITDA (Base Case) | B40: ='Income Statement'!F39 -> 14899.598 | C40: ='Income Statement'!F39 -> 14899.598 | D40: ='Income Statement'!F39 -> 14899.598
A41: Implied EV | B41: =B39*B40 -> 446987.93 | C41: =C39*C40 -> 506586.32 | D41: =D39*D40 -> 566184.71
A42: Implied Equity Value | B42: =B41-$B$25 -> 452336.93 | C42: =C41-$B$25 -> 511935.32 | D42: =D41-$B$25 -> 571533.71
A43: Implied Price (EV/EBITDA) | B43: =B42/$B$21 -> 1016.0308 | C43: =C42/$B$21 -> 1149.8996 | D43: =D42/$B$21 -> 1283.7684
A44: Upside / (Downside) vs Current | B44: =(B43-$B$20)/$B$20 -> 0.010674261 | C44: =(C43-$B$20)/$B$20 -> 0.1438373 | D44: =(D43-$B$20)/$B$20 -> 0.27700034
